LICENSE.txt
MANIFEST.in
README.md
setup.py
henon_map/__init__.py
henon_map/cpu_henon_core.py
henon_map/gpu_henon_core.py
henon_map.egg-info/PKG-INFO
henon_map.egg-info/SOURCES.txt
henon_map.egg-info/dependency_links.txt
henon_map.egg-info/requires.txt
henon_map.egg-info/top_level.txt
test/test_equality.py