Metadata-Version: 1.0
Name: henon-map
Version: 0.0.11
Summary: Henon map implemented in Numba
Home-page: UNKNOWN
Author: Carlo Emilio Montanari
Author-email: carlidel95@gmail.com
License: MIT
Platform: UNKNOWN
